chompack-2.3.3.dist-info/WHEEL
chompack-2.3.3.dist-info/top_level.txt
chompack-2.3.3.dist-info/METADATA
chompack-2.3.3.dist-info/RECORD
chompack/symbolic.py
chompack/cbase.cpython-34m.so
chompack/pfcholesky.py
chompack/__init__.py
chompack/maxchord.py
chompack/misc.py
chompack/mcs.py
chompack/_version.py
chompack/base.py
chompack/conversion.py
chompack/.libs/libopenblasp-r0-39a31c03.2.18.so
chompack/.libs/libgfortran-ed201abd.so.3.0.0
chompack/pybase/projected_inverse.py
chompack/pybase/trsm.py
chompack/pybase/mrcompletion.py
chompack/pybase/plot.py
chompack/pybase/edmcompletion.py
chompack/pybase/__init__.py
chompack/pybase/completion.py
chompack/pybase/psdcompletion.py
chompack/pybase/cholesky.py
chompack/pybase/llt.py
chompack/pybase/hessian.py
chompack/pybase/trmm.py
