Metadata-Version: 2.0
Name: chompack
Version: 2.3.3
Summary: Library for chordal matrix computations
Home-page: http://cvxopt.github.io/chompack/
Author: Martin S. Andersen, Lieven Vandenberghe
Author-email: martin.skovgaard.andersen@gmail.com, vandenbe@ee.ucla.edu
License: GNU GPL version 3
Download-URL: https://github.com/cvxopt/chompack/archive/2.3.3.tar.gz
Platform: UNKNOWN
Classifier: Development Status :: 4 - Beta
Classifier: Intended Audience :: Science/Research
Classifier: License :: OSI Approved :: GNU General Public License v3 (GPLv3)
Classifier: Operating System :: OS Independent
Classifier: Programming Language :: C
Classifier: Programming Language :: Python
Classifier: Programming Language :: Python :: 3
Classifier: Topic :: Scientific/Engineering
Requires-Dist: cvxopt (>=1.2.0)
Requires-Dist: mkl
